jetblack_datagram/__init__.py
jetblack_datagram/datagram.py
jetblack_datagram-0.4.1.dist-info/LICENSE
jetblack_datagram-0.4.1.dist-info/WHEEL
jetblack_datagram-0.4.1.dist-info/METADATA
jetblack_datagram-0.4.1.dist-info/RECORD
