Metadata-Version: 2.1
Name: jetblack-datagram
Version: 0.4.1
Summary: A Python 3 asyncio datagram library
Home-page: https://github.com/rob-blackbourn/jetblack-datagram
License: Apache-2.0
Author: Rob Blackbourn
Author-email: rob.blackbourn@gmail.com
Requires-Python: >=3.8,<4.0
Classifier: License :: OSI Approved :: Apache Software License
Classifier: Programming Language :: Python :: 3
Classifier: Programming Language :: Python :: 3.8
Classifier: Programming Language :: Python :: 3.9
Project-URL: Repository, https://github.com/rob-blackbourn/jetblack-datagram
